hexcore/__init__.py
hexcore/__init__.pyi
hexcore/config.py
hexcore/config.pyi
hexcore/types.py
hexcore/types.pyi
hexcore/application/__init__.py
hexcore/application/__init__.pyi
hexcore/application/dtos/__init__.py
hexcore/application/dtos/__init__.pyi
hexcore/application/dtos/base.py
hexcore/application/dtos/base.pyi
hexcore/application/use_cases/__init__.py
hexcore/application/use_cases/__init__.pyi
hexcore/application/use_cases/base.py
hexcore/application/use_cases/base.pyi
hexcore/domain/__init__.py
hexcore/domain/__init__.pyi
hexcore/domain/base.py
hexcore/domain/base.pyi
hexcore/domain/events.py
hexcore/domain/events.pyi
hexcore/domain/exceptions.py
hexcore/domain/exceptions.pyi
hexcore/domain/repositories.py
hexcore/domain/repositories.pyi
hexcore/domain/services.py
hexcore/domain/services.pyi
hexcore/domain/uow.py
hexcore/domain/uow.pyi
hexcore/domain/auth/__init__.py
hexcore/domain/auth/__init__.pyi
hexcore/domain/auth/permissions.py
hexcore/domain/auth/permissions.pyi
hexcore/domain/auth/value_objects.py
hexcore/domain/auth/value_objects.pyi
hexcore/infrastructure/__init__.py
hexcore/infrastructure/__init__.pyi
hexcore/infrastructure/cli.py
hexcore/infrastructure/cli.pyi
hexcore/infrastructure/api/__init__.py
hexcore/infrastructure/api/__init__.pyi
hexcore/infrastructure/api/utils.py
hexcore/infrastructure/api/utils.pyi
hexcore/infrastructure/cache/__init__.py
hexcore/infrastructure/cache/__init__.pyi
hexcore/infrastructure/cache/cache_backends/__init__.py
hexcore/infrastructure/cache/cache_backends/__init__.pyi
hexcore/infrastructure/cache/cache_backends/memory.py
hexcore/infrastructure/cache/cache_backends/memory.pyi
hexcore/infrastructure/cache/cache_backends/redis.py
hexcore/infrastructure/cache/cache_backends/redis.pyi
hexcore/infrastructure/events/__init__.py
hexcore/infrastructure/events/__init__.pyi
hexcore/infrastructure/events/events_backends/__init__.py
hexcore/infrastructure/events/events_backends/__init__.pyi
hexcore-2.1.1.dist-info/licenses/LICENSE
hexcore-2.1.1.dist-info/METADATA
hexcore-2.1.1.dist-info/WHEEL
hexcore-2.1.1.dist-info/entry_points.txt
hexcore-2.1.1.dist-info/top_level.txt
hexcore-2.1.1.dist-info/RECORD
