Metadata-Version: 2.4
Name: hexcore
Version: 2.1.1
Summary: Núcleo reutilizable para proyectos Python con arquitectura hexagonal y event handling. Provee abstracciones, utilidades y contratos para DDD, eventos y desacoplamiento de infraestructura.
Author-email: "David Latosefki (Indroic)" <indroic@outlook.com>
License-Expression: MIT
Requires-Python: >=3.12
License-File: LICENSE
Requires-Dist: aiosqlite>=0.21.0
Requires-Dist: alembic>=1.16.5
Requires-Dist: async-typer>=0.1.10
Requires-Dist: asyncpg>=0.30.0
Requires-Dist: beanie>=2.0.0
Requires-Dist: build>=1.3.0
Requires-Dist: fastapi>=0.116.1
Requires-Dist: pika>=1.3.2
Requires-Dist: pydantic>=2.11.7
Requires-Dist: redis>=6.4.0
Requires-Dist: sqlalchemy>=2.0.43
Requires-Dist: twine>=6.2.0
Requires-Dist: typer>=0.17.3
Dynamic: license-file
